sdsbl-1.0.0.1.dist-info/DESCRIPTION.rst
sdsbl-1.0.0.1.dist-info/METADATA
sdsbl-1.0.0.1.dist-info/RECORD
sdsbl-1.0.0.1.dist-info/WHEEL
sdsbl-1.0.0.1.dist-info/metadata.json
sdsbl-1.0.0.1.dist-info/top_level.txt
url_package/SDSBL.py
url_package/__init__.py
url_package/gglsbl/__init__.py
url_package/gglsbl/_version.py
url_package/gglsbl/client.py
url_package/gglsbl/protocol.py
url_package/gglsbl/storage.py
url_package/gglsbl/utils.py
